{"that2":{"class":["numeric"],"type":"double","length":1,"str":"num 89369114"},"t_p":{"class":["integer"],"type":"integer","length":1,"str":"int 34"},"cvhat_ybar":{"class":["numeric"],"type":"double","length":1,"str":"num 0"},"frame":{"class":["data.frame"],"type":"list","length":14,"str":"'data.frame':\t300 obs. of  14 variables:","names":["county","state","acres92","acres87","acres82","farms92","farms87","farms82","largef92","largef87","largef82","smallf92","smallf87","smallf82"]},"class_survey":{"class":["data.frame"],"type":"list","length":4,"str":"'data.frame':\t28 obs. of  4 variables:","names":["Index","Course","Textbook","Graduation"]},"cvhat_phat":{"class":["numeric"],"type":"double","length":1,"str":"num 0"},"basball_data":{"class":["data.frame"],"type":"list","length":30,"str":"'data.frame':\t150 obs. of  30 variables:","names":["V1","V2","V3","V4","V5","V6","V7","V8","V9","V10","V11","V12","V13","V14","V15","V16","V17","V18","V19","V20","V21","V22","V23","V24","V25","V26","V27","V28","V29","V30"]},"ybar_p":{"class":["numeric"],"type":"double","length":1,"str":"num 4.11"},"se_that":{"class":["numeric"],"type":"double","length":1,"str":"num 0"},"se_phat":{"class":["numeric"],"type":"double","length":1,"str":"num 0"},"cvhat_that":{"class":["numeric"],"type":"double","length":1,"str":"num 0"},"that":{"class":["numeric"],"type":"double","length":1,"str":"num 89369114"},"phat":{"class":["numeric"],"type":"double","length":1,"str":"num 0.51"},"phat2":{"class":["numeric"],"type":"double","length":1,"str":"num 0.51"},"se_ybar":{"class":["numeric"],"type":"double","length":1,"str":"num 0"},"srssam":{"class":["data.frame"],"type":"list","length":16,"str":"'data.frame':\t300 obs. of  16 variables:","names":["county","state","acres92","acres87","acres82","farms92","farms87","farms82","largef92","largef87","largef82","smallf92","smallf87","smallf82","sampwts","lt200k"]},"N":{"class":["integer"],"type":"integer","length":1,"str":"int 300"},"ybar":{"class":["numeric"],"type":"double","length":1,"str":"num 297897"},"n":{"class":["numeric"],"type":"double","length":1,"str":"num 300"},"ybar2":{"class":["numeric"],"type":"double","length":1,"str":"num 297897"},"prop_p":{"class":["numeric"],"type":"double","length":1,"str":"num 0.214"},"s":{"class":["numeric"],"type":"double","length":1,"str":"num 344552"}}
